{
    "@context": "http://schema.org",
    "@type": "Dataset",
    "name": "PrivateVPN Speed Tests for Best VPNs for UAE and Dubai",
    "description": "This chart shows the speed test results for PrivateVPN when used for best vpns for uae and dubai.",
    "creator": {
        "@type": "Organization",
        "name": "Comparitech Ltd"
    },
    "license": "https://creativecommons.org/licenses/by/4.0/",
    "variableMeasured": [
        {
            "@type": "PropertyValue",
            "name": "AM",
            "value": 102.91,
            "unitText": "Mbps"
        },
        {
            "@type": "PropertyValue",
            "name": "Noon",
            "value": 107.29,
            "unitText": "Mbps"
        },
        {
            "@type": "PropertyValue",
            "name": "PM",
            "value": 117.3,
            "unitText": "Mbps"
        },
        {
            "@type": "PropertyValue",
            "name": "Average",
            "value": 109.17,
            "unitText": "Mbps"
        },
        {
            "@type": "PropertyValue",
            "name": "Average of other providers",
            "value": 169.32,
            "unitText": "Mbps"
        }
    ],
    "measurementTechnique": "Speed test"
}