{
    "@context": "http://schema.org",
    "@type": "Dataset",
    "name": "Speed & availability: Overall Score for Best VPNs for BBC iPlayer",
    "description": "This chart shows the speed & availability: overall score for each VPN provider when used for best vpns for bbc iplayer.",
    "creator": {
        "@type": "Organization",
        "name": "Comparitech Ltd"
    },
    "license": "https://creativecommons.org/licenses/by/4.0/",
    "variableMeasured": [
        {
            "@type": "PropertyValue",
            "name": "NordVPN - Speed & availability: Overall Score",
            "value": 7.9,
            "unitText": "Score out of 10"
        },
        {
            "@type": "PropertyValue",
            "name": "Surfshark - Speed & availability: Overall Score",
            "value": 8.0,
            "unitText": "Score out of 10"
        },
        {
            "@type": "PropertyValue",
            "name": "IPVanish - Speed & availability: Overall Score",
            "value": 7.5,
            "unitText": "Score out of 10"
        },
        {
            "@type": "PropertyValue",
            "name": "ExpressVPN - Speed & availability: Overall Score",
            "value": 8.7,
            "unitText": "Score out of 10"
        },
        {
            "@type": "PropertyValue",
            "name": "CyberGhost - Speed & availability: Overall Score",
            "value": 6.6,
            "unitText": "Score out of 10"
        },
        {
            "@type": "PropertyValue",
            "name": "PIA - Speed & availability: Overall Score",
            "value": 7.9,
            "unitText": "Score out of 10"
        },
        {
            "@type": "PropertyValue",
            "name": "PureVPN - Speed & availability: Overall Score",
            "value": 6.8,
            "unitText": "Score out of 10"
        },
        {
            "@type": "PropertyValue",
            "name": "Proton VPN - Speed & availability: Overall Score",
            "value": 5.0,
            "unitText": "Score out of 10"
        },
        {
            "@type": "PropertyValue",
            "name": "PrivateVPN - Speed & availability: Overall Score",
            "value": 3.6,
            "unitText": "Score out of 10"
        }
    ],
    "measurementTechnique": "Score out of 10"
}