{
    "@context": "http://schema.org",
    "@type": "Dataset",
    "name": "Surfshark Speed Tests for watching 10 Play",
    "description": "This chart shows the speed test results for Surfshark when used for watching 10 play.",
    "creator": {
        "@type": "Organization",
        "name": "Comparitech Ltd"
    },
    "license": "https://creativecommons.org/licenses/by/4.0/",
    "variableMeasured": [
        {
            "@type": "PropertyValue",
            "name": "AM",
            "value": 185.22,
            "unitText": "Mbps"
        },
        {
            "@type": "PropertyValue",
            "name": "Noon",
            "value": 181.4,
            "unitText": "Mbps"
        },
        {
            "@type": "PropertyValue",
            "name": "PM",
            "value": 175.73,
            "unitText": "Mbps"
        },
        {
            "@type": "PropertyValue",
            "name": "Average",
            "value": 180.78,
            "unitText": "Mbps"
        },
        {
            "@type": "PropertyValue",
            "name": "Average of other providers",
            "value": 131.67,
            "unitText": "Mbps"
        }
    ],
    "measurementTechnique": "Speed test"
}