{
    "@context": "http://schema.org",
    "@type": "Dataset",
    "name": "ExpressVPN Speed Tests for Best VPNs for Linux",
    "description": "This chart shows the speed test results for ExpressVPN when used for best vpns for linux.",
    "creator": {
        "@type": "Organization",
        "name": "Comparitech Ltd"
    },
    "license": "https://creativecommons.org/licenses/by/4.0/",
    "variableMeasured": [
        {
            "@type": "PropertyValue",
            "name": "AM (Japan)",
            "value": 19.95,
            "unitText": "Mbps"
        },
        {
            "@type": "PropertyValue",
            "name": "AM (US)",
            "value": 34.99,
            "unitText": "Mbps"
        },
        {
            "@type": "PropertyValue",
            "name": "AM (UK)",
            "value": 25.72,
            "unitText": "Mbps"
        }
    ],
    "measurementTechnique": "Speed test"
}