{
    "@context": "http://schema.org",
    "@type": "Dataset",
    "name": "CyberGhost Speed Tests for NordVPN for torrenting",
    "description": "This chart shows the speed test results for CyberGhost when used for nordvpn for torrenting.",
    "creator": {
        "@type": "Organization",
        "name": "Comparitech Ltd"
    },
    "license": "https://creativecommons.org/licenses/by/4.0/",
    "variableMeasured": [
        {
            "@type": "PropertyValue",
            "name": "AM",
            "value": 207.63,
            "unitText": "Mbps"
        },
        {
            "@type": "PropertyValue",
            "name": "Noon",
            "value": 194.06,
            "unitText": "Mbps"
        },
        {
            "@type": "PropertyValue",
            "name": "PM",
            "value": 191.5,
            "unitText": "Mbps"
        },
        {
            "@type": "PropertyValue",
            "name": "Average",
            "value": 197.72,
            "unitText": "Mbps"
        },
        {
            "@type": "PropertyValue",
            "name": "Average of other providers",
            "value": 175.73,
            "unitText": "Mbps"
        }
    ],
    "measurementTechnique": "Speed test"
}