{
    "@context": "http://schema.org",
    "@type": "Dataset",
    "name": "NordVPN Speed Tests for Accessing Discord in the UAE",
    "description": "This chart shows the speed test results for NordVPN when used for accessing discord in the uae.",
    "creator": {
        "@type": "Organization",
        "name": "Comparitech Ltd"
    },
    "license": "https://creativecommons.org/licenses/by/4.0/",
    "variableMeasured": [
        {
            "@type": "PropertyValue",
            "name": "AM",
            "value": 198.07,
            "unitText": "Mbps"
        },
        {
            "@type": "PropertyValue",
            "name": "Noon",
            "value": 169.7,
            "unitText": "Mbps"
        },
        {
            "@type": "PropertyValue",
            "name": "PM",
            "value": 161.87,
            "unitText": "Mbps"
        },
        {
            "@type": "PropertyValue",
            "name": "Average",
            "value": 176.54,
            "unitText": "Mbps"
        },
        {
            "@type": "PropertyValue",
            "name": "Average of other providers",
            "value": 99.01,
            "unitText": "Mbps"
        }
    ],
    "measurementTechnique": "Speed test"
}