{
    "@context": "http://schema.org",
    "@type": "Dataset",
    "name": "CyberGhost Speed Tests for Best VPNs for Xbox One",
    "description": "This chart shows the speed test results for CyberGhost when used for best vpns for xbox one.",
    "creator": {
        "@type": "Organization",
        "name": "Comparitech Ltd"
    },
    "license": "https://creativecommons.org/licenses/by/4.0/",
    "variableMeasured": [
        {
            "@type": "PropertyValue",
            "name": "AM",
            "value": 115.64,
            "unitText": "Mbps"
        },
        {
            "@type": "PropertyValue",
            "name": "Noon",
            "value": 119.3,
            "unitText": "Mbps"
        },
        {
            "@type": "PropertyValue",
            "name": "PM",
            "value": 122.72,
            "unitText": "Mbps"
        },
        {
            "@type": "PropertyValue",
            "name": "Average",
            "value": 119.21,
            "unitText": "Mbps"
        },
        {
            "@type": "PropertyValue",
            "name": "Average of other providers",
            "value": 144.9,
            "unitText": "Mbps"
        }
    ],
    "measurementTechnique": "Speed test"
}