{
    "@context": "http://schema.org",
    "@type": "Dataset",
    "name": "IPVanish Speed Tests for Thailand IP address",
    "description": "This chart shows the speed test results for IPVanish when used for thailand ip address.",
    "creator": {
        "@type": "Organization",
        "name": "Comparitech Ltd"
    },
    "license": "https://creativecommons.org/licenses/by/4.0/",
    "variableMeasured": [
        {
            "@type": "PropertyValue",
            "name": "AM",
            "value": 139.41,
            "unitText": "Mbps"
        },
        {
            "@type": "PropertyValue",
            "name": "Noon",
            "value": 141.4,
            "unitText": "Mbps"
        },
        {
            "@type": "PropertyValue",
            "name": "PM",
            "value": 140.38,
            "unitText": "Mbps"
        },
        {
            "@type": "PropertyValue",
            "name": "Average",
            "value": 140.39,
            "unitText": "Mbps"
        },
        {
            "@type": "PropertyValue",
            "name": "Average of other providers",
            "value": 137.33,
            "unitText": "Mbps"
        }
    ],
    "measurementTechnique": "Speed test"
}