{
    "@context": "http://schema.org",
    "@type": "Dataset",
    "name": "CyberGhost Speed Tests for removing geo-blocking with a VPN and change your location",
    "description": "This chart shows the speed test results for CyberGhost when used for removing geo-blocking with a vpn and change your location.",
    "creator": {
        "@type": "Organization",
        "name": "Comparitech Ltd"
    },
    "license": "https://creativecommons.org/licenses/by/4.0/",
    "variableMeasured": [
        {
            "@type": "PropertyValue",
            "name": "AM",
            "value": 181.15,
            "unitText": "Mbps"
        },
        {
            "@type": "PropertyValue",
            "name": "Noon",
            "value": 177.17,
            "unitText": "Mbps"
        },
        {
            "@type": "PropertyValue",
            "name": "PM",
            "value": 187.3,
            "unitText": "Mbps"
        },
        {
            "@type": "PropertyValue",
            "name": "Average",
            "value": 181.88,
            "unitText": "Mbps"
        },
        {
            "@type": "PropertyValue",
            "name": "Average of other providers",
            "value": 173.65,
            "unitText": "Mbps"
        }
    ],
    "measurementTechnique": "Speed test"
}